README.txt
setup.cfg
setup.py
wikiup.cfg
wikiup.py
WikiUp.egg-info/PKG-INFO
WikiUp.egg-info/SOURCES.txt
WikiUp.egg-info/dependency_links.txt
WikiUp.egg-info/entry_points.txt
WikiUp.egg-info/requires.txt
WikiUp.egg-info/top_level.txt