Metadata-Version: 1.0
Name: WikiUp
Version: 1.1
Summary: Wiki page uploading command plugin for setuptools
Home-page: http://cheeseshop.python.org/pypi/WikiUp
Author: Phillip J. Eby
Author-email: peak@eby-sarna.com
License: PSF or ZPL
Platform: UNKNOWN
Classifier: Framework :: Setuptools Plugin
